{
  "brewery": [
    {
      "title": "산머루농원",
      "location": "경기 파주시 적성면 객현리 67-1",
      "phone": "031-958-4558",
      "link": "http://www.sanmeoru.com",
      "alwaysvisit": false,
      "reservation": true,
      "visitcount": 2420,
      "number": 1,
      "main": "산머루 농원 감악산 머루주 12도",
      "content": "산머루농원영농조합법인은 지난 1979년 서충원 대표의 부친인 서우석씨가 파주시 적성면 일대에 머루재배를 시작하면서 태동했다. 1980년에는 산머루 재배기술을 확립했고 1990년에는 인근 농가에 재배기술보급하는 등 생산기반을 갖추고 1995년 5월 1일 산머루 가공공장을 설립하면서 산머루농원영농조합법인으로 등록했다. 산머루농원영농조합법인은 48개 농가와 계약재배 물량은 전량 수매를 원칙으로 한다. 판매를 하지 못해 생산물량이 창고에 쌓이는 한이 있어도 계약한 물량은 전량 수매해 농가들이 안정적으로 생산할 수 있도록 배려한다. 농가와 계약재배방식으로 생산기반을 갖추고 지난 1997년 9월 머루주와 머루즙 첫 제품을 출시하면서 본격적인 마케팅에 돌입했다. 산머루 가 공공장에서는 연간 4 00톤 정도의 머루주와 머루즙을 생산해 연간 15억원의 매출을 올리고 있다. 하지만 산머루농원영농조합법인은 10여년 동안 가족과 친척중심으로 현실에 안주하는 경영방식이 이어지면서 매출은 늘지 않고 인건비와 건물유지비 등 고정비용만 지속적으로 늘어나면서 심각한 경영위기를 맞게 된다. 이에 따라 2010년 전 직원 해고 후 능력있는 직원들을 유임시키고 2년간 전문경영인 영입을 통한 경영쇄신을 한데 이어 2012년 현 서충원대표를 취임시켜 새로운 변화와 쇄신을 모색했다.",
      "activity": [],
      "mainImage": "https://www.nongsaro.go.kr/cms_contents/1100/202753_MF_BIMG_01.jpg"
    },
    {
      "title": "배상면주가",
      "location": "경기도 포천시 화현면 화현리 512",
      "phone": "031-531-9300",
      "link": "https://www.soolsool.co.kr/",
      "alwaysvisit": true,
      "reservation": false,
      "visitcount": 3320,
      "number": 2,
      "main": "느린마을 막걸리(봄, 여름, 가을, 겨울), 느린마을 약주, 느린마을 소주",
      "content": "아시아 최고의 술 문화 기업이란 단지 규모가 큰 회사를 말하는 것이 아닙니다. 아시아권에서 '술' 또는 '술 문화'와 관련하여 최고의 기업이 되고자 하는 것입니다. 배상면주가는 아시아의 수 많은 술 회사들 중에서 술과 관련된 문화를 다듬고 가꾸어 퍼트리는 선구자가 되겠습니다.  한국 전통술의 큰 스승 故배상면 선생의 이름을 기업명으로 내세울 만큼 정성으로 빚은 술에 대한 자부심이 있습니다. 대를 잇는 한국 술에 대한 사랑과 열정은 현 시대에 맞게 세대를 이어 계속 재현되고 있습니다.",
      "activity": [],
      "mainImage": "https://www.soolsool.co.kr/html/soolsool/_images/sub/business_03.jpg"
    },
    {
      "title": "우리술",
      "location": "경기 가평군 하면 대보간선로 26",
      "phone": "031-585-8525",
      "link": "http://www.woorisool.kr",
      "alwaysvisit": true,
      "reservation": false,
      "visitcount": 2350,
      "number": 3,
      "main": "가평잣 생 막걸리",
      "content": "끊임없는 도전으로 막걸리의 세계화를 위해 노력하는 우리술, 어느 안주에나 어울리는 깔끔한 막걸리 맛을 유지하겠습니다. 어디서나 막걸리를 즐길 수 있도록 다양한 연구를 하겠습니다.",
      "activity": [
        {
          "activityLink": "https://www.woorisool.kr/brewery",
          "title": "막걸리 공장 견학 및 막걸리 시음 + 선물 증정",
          "description": "우리술 막걸리 생산 공장은 경기도내 가장 큰 규모로 일일 최대 10만리터, 연간 3만톤을 생산하고 있습니다. 막걸리업계 내 최초로 HACCP을 인증 받은 제 2공장의 생산모습과 지금도 더 좋은 품질을 위해 매일 품질검사와 연구를 거듭하는 연구실의 모습도 직접 확인해보세요!",
          "price": "10,000"
        },
        {
          "activityLink": "https://www.woorisool.kr/brewery",
          "title": "막걸리 공장 견학 및 막걸리 빚기 체험 그리고 다양한 막걸리 시음 ",
          "description": "막걸리의 제조과정을 배우고 직접 나만의 막걸리를 담가보는 특별한 체험을 경험해보세요. 우리술이 생산하는 다양한 종류의 막걸리(쌀, 잣, 고구마, 땅콩, 옥수수)를 직접 시음해보실 수 있는 시간도 준비되어있습니다. 추가로 막걸리 선물 세트는 덤!",
          "price": "30,000"
        }
      ],
      "mainImage": "https://newsimg.sedaily.com/2023/05/25/29PPTIU4EZ_2.jpg"
    },
    {
      "title": "그린영농조합",
      "location": "경기도 안산시 단원구 뻐꾹산길 107",
      "phone": "032-886-9873",
      "link": "http://www.grandcoteau.co.kr",
      "alwaysvisit": true,
      "reservation": false,
      "visitcount": 1845,
      "number": 4,
      "main": "그랑꼬도 레드와인 M56",
      "content": "와인의 품질은 70%가 포도밭에서 결정된다고 합니다. 좋은 포도밭에서 좋은 포도로 만든 와인이 제대로 된 빛깔과 맛 그리고 향을 지니게 된다는 뜻입니다. 사람의 정성과 좋은 기술이 만나야 비로소 와인이라는 예술품을 완성해 낼 수 있습니다. 그랑꼬또의 기술과 정성, 맛을 경험하십시오. 잊을 수 없는 특별함을 선사할 것입니다.",
      "activity": [],
      "mainImage": "https://modo-phinf.pstatic.net/20170616_291/1497585683702jDpIx_JPEG/mosaGYqG8w.jpeg?type=w720"
    },
    {
      "title": "배혜정도가",
      "location": "경기도 화성시 정남면 서봉로 835",
      "phone": "031-354-9376",
      "link": "http://www.baedoga.co.kr/",
      "alwaysvisit": false,
      "reservation": true,
      "visitcount": 2301,
      "number": 5,
      "main": "배혜정도가 우곡소주 25도, 호랑이 막걸리, 우곡생주",
      "content": "프리미엄 탁주의 선두주자이자 대명사로 자리매김한 [배혜정도가]의 다년간의 기술력을 바탕으로, 한국형 글로번 증류주의 고급화 및 세계화를 위해 지속적인 연구개발을 할 것을 약속드리며 언젠가 한국한 증류주가 명주 반열에 들어가는 날을 꿈꾸며 앞으로 더욱 발전해나가겠습니다.",
      "activity": [],
      "mainImage": "http://www.baedoga.co.kr/img/service/01.jpg"
    },
    {
      "title": "밝은세상영농조합",
      "location": "경기도 평택시 포승읍 충열길 37",
      "phone": "031-683-0981",
      "link": "https://www.instagram.com/tigercalyx/?hl=ko",
      "alwaysvisit": false,
      "reservation": true,
      "visitcount": 1590,
      "number": 6,
      "main": "소호, 호랑이배꼽 막걸리",
      "content": "기상하는 호랑이 형상 한반도의 배꼽자리, 경기도 평택의 자연을 담아 우리술을 빚습니다.",
      "activity": [
        {
          "activityLink": "https://thesooltourism.com/reservation/input.do",
          "title": "계절막걸리 빚기",
          "description": "우리술 막걸리 생산 공장은 경기도내 가장 큰 규모로 일일 최대 10만리터, 연간 3만톤을 생산하고 있습니다. 막걸리업계 내 최초로 HACCP을 인증 받은 제 2공장의 생산모습과 지금도 더 좋은 품질을 위해 매일 품질검사와 연구를 거듭하는 연구실의 모습도 직접 확인해보세요!",
          "price": "50,000"
        },
        {
          "activityLink": "https://thesooltourism.com/reservation/input.do",
          "title": "시음체험",
          "description": "호랑이배꼽 양조장의 술들을 시음하며 이야기합니다.",
          "price": "20,000"
        }
      ],
      "mainImage": "http://www.lampcook.com/wi_files/food_story/brewery_story/story2_6_2.jpg"
    },
    {
      "title": "좋은술",
      "location": "경기 평택시 오성면 숙성뜰길 108",
      "phone": "031-681-8929",
      "link": "https://jsul.modoo.at/",
      "alwaysvisit": true,
      "reservation": false,
      "visitcount": 1557,
      "number": 7,
      "main": "천비향 약주",
      "content": "천비향은 경기도 평택 숙성리 마을의 좋은술 양조장에서 생산되는 고귀한 전통주입니다. 이 술은 평택의 풍부한 자연과 양조장의 정성을 담아내어 많은 사람들에게 사랑받고 있습니다. 숙성리 마을은 드넓은 평야와 강변이 어우러져 아름다운 자연 경관을 자랑합니다. 여름에는 푸른 벼가 들판을 가득 채우고, 가을이 되면 황금빛 벼가 물결치는 환상적인 풍경을 연출합니다. 좋은술 양조장은 이 자연의 선물을 활용하여, 맑고 깨끗한 강물과 평택의 비옥한 토양에서 자란 쌀을 사용해 술을 빚습니다.",
      "activity": [
        {
          "activityLink": "https://thesooltourism.com/reservation/input.do",
          "title": "막걸리만들기",
          "description": "막걸리를 직접 만들어보는 체험 프로그램입니다. 막걸리의 역사와 제조 과정을 배우고, 막걸리를 빚어보며 한국 전통 문화에 대해 깊이 이해할 수 있는 시간을 가집니다.",
          "price": "30,000"
        },
        {
          "activityLink": "https://thesooltourism.com/reservation/input.do",
          "title": "막걸리잼만들기",
          "description": "막걸리를 활용한 특별한 디저트, 막걸리 잼을 직접 만들어보는 체험 프로그램입니다. 막걸리 잼의 독특한 맛을 경험하며, 직접 만든 잼을 가져갈 수 있는 기회를 가집니다.",
          "price": "20,000"
        }
      ],
      "mainImage": "https://lh3.googleusercontent.com/p/AF1QipNnqcttNUfX9hbPHpH_ftPfCFvFTBJ83f7jGkcB=s680-w680-h510"
    },
    {
      "title": "술샘",
      "location": "경기도 용인시 처인구 양지면 죽양대로 2298-1",
      "phone": "070-4218-5225",
      "link": "http://www.sulseam.com",
      "alwaysvisit": true,
      "reservation": false,
      "visitcount": 1971,
      "number": 8,
      "main": "술취한 원숭이, 미르40",
      "content": "술샘은 지역에서 계약 재배한 쌀로 다양한 주종의 우리술을 만들어 판매하는 양조장입니다.",
      "activity": [
        {
          "activityLink": "https://thesooltourism.com/reservation/input.do",
          "title": "시음",
          "description": "술샘에서 생산되는 대표 5종의 술을 시음해 보고 주종별 특성에 대해 이야기를 나누는 시간",
          "price": "20,000"
        },
        {
          "activityLink": "https://thesooltourism.com/reservation/input.do",
          "title": "시음 및 찹쌀막걸리 빚기",
          "description": "술샘의 술 5종 시음과 더불어 찹쌀 막걸리 빚기 체험을 통해 우리술의 발효원리를 이해할 수 있는 프로그램",
          "price": "40,000"
        }
      ],
      "mainImage": "https://lh3.googleusercontent.com/p/AF1QipNP0kZzl-q6TILJA-Phom-MCmBDWun15Amyt4kc=s680-w680-h510"
    },
    {
      "title": "신평양조장",
      "location": "충남 당진시 신평면 신평로 813",
      "phone": "041-362-6080",
      "link": "http://www.koreansul.co.kr",
      "alwaysvisit": true,
      "reservation": false,
      "visitcount": 1334,
      "number": 15,
      "main": "백련 생막걸리 Snow 6%, 백련 막걸리 Misty, 7%, 백련 맑은술, 12%",
      "content": "충청남도 당진시 신평면에 위치한 '신평양조장 '은 1933년에 설립되어 할아버지에서 아버지로, 아버지에서 또 아들로 3대째 이어지고 있는 전통 양조장입니다.",
      "activity": [
        {
          "activityLink": "https://koreansul.modoo.at/?link=4jw74a4f",
          "title": "막걸리 빚기 체험",
          "description": "전통주 강의, 막걸리 빚기, 제품 시음",
          "price": "25,000"
        },
        {
          "activityLink": "https://koreansul.modoo.at/?link=4jw74a4f",
          "title": "명예 막걸리 소믈리에",
          "description": "한국 막걸리 협회 회장 인증, 명예 막걸리 소믈리에 자격증 프로그램",
          "price": "25,000"
        },
        {
          "activityLink": "https://koreansul.modoo.at/?link=4jw74a4f",
          "title": "증류주 내리기 체험 ",
          "description": "증류주 강의, 소주 내리기 체험",
          "price": "45,000"
        },
        {
          "activityLink": "https://koreansul.modoo.at/?link=4jw74a4f",
          "title": "누룩전, 쿠키 만들기",
          "description": "신평양조장에서만 맛 볼 수 있는 쌀누룩과 견과류, 꿀을 넣어 빝는 누룩전 만들기",
          "price": "25,000"
        }
      ],
      "mainImage": "https://lh3.googleusercontent.com/p/AF1QipMiDin34Mfc_bwncBVbN40UM79kOzdKEVc6nFuH=s680-w680-h510"
    },
    {
      "title": "예산사과와인",
      "location": "충남 예산군 고덕면 대몽로 107-25",
      "phone": "041-337-9584",
      "link": "http://www.chusawine.com",
      "alwaysvisit": true,
      "reservation": false,
      "visitcount": 1481,
      "number": 16,
      "main": "추사 애플와인",
      "content": "충남 예산에서 사과 재배, 수확, 와인 발효와 숙성, 체험 관광까지 결합되어 있는 복합적 문화공간의 유럽 스타일 와이너리입니다.",
      "activity": [
        {
          "activityLink": "https://thesooltourism.com/reservation/input.do",
          "title": "와이너리 투어와 시음",
          "description": "와인생산시설을 견학하고 와인과 증류주를 시음하는 체험",
          "price": "10,000"
        },
        {
          "activityLink": "https://thesooltourism.com/reservation/input.do",
          "title": "사과 수확 체",
          "description": "사과 수확 체험(9월~ 11월 중순)",
          "price": "무료"
        }
      ],
      "mainImage": "https://lh3.googleusercontent.com/p/AF1QipNn6b4LcMVn3etWYCHuvx8Bhzen0KXE5ovvYF_Z=s680-w680-h510"
    },
    {
      "title": "양촌양조",
      "location": "충남 논산시 양촌면 매죽헌로1665번길 14-9",
      "phone": "041-741-2011",
      "link": "http://www.yangchon.co.kr/",
      "alwaysvisit": true,
      "reservation": false,
      "visitcount": 1635,
      "number": 20,
      "main": "우렁이쌀청주",
      "content": "1930년 건립된 주조장은 막걸리 주조만을 위해 설계된 목조건물로 재래식 자연 통풍구조를 갖추어 막걸리 주조시 발생되는 상승온도와 습도 등을 자연적으로 조절할수 있도록 설계되었으며 지하1층 반지하는 막걸리 발효 및 숙성을 위한 공간이며 반이층은 반지하 공간과 연결된 통로를 이용하여 고두밥을 냉각시킨 뒤 전달하는 구조로 지어졌으나, 현재는 고두밥을 전달하지는 않고 투명창으로 하여 발효되는 술을 관람할 수 있도록 개조한 상태이다.",
      "activity": [
        {
          "activityLink": "https://thesooltourism.com/reservation/input.do",
          "title": "견학",
          "description": "제조과정설명 및 견학 및 시음행사",
          "price": "10,000"
        }
      ],
      "mainImage": "https://d38cxpfv0ljg7q.cloudfront.net/admin_contents/origin/QjQp-1622695409854-yang-chon-yang-jo.png"
    },
    {
      "title": "한산소곡주",
      "location": "충남 서천군 한산면 충절로 1118",
      "phone": "041-951-0290",
      "link": "http://www.sogokju.co.kr",
      "alwaysvisit": true,
      "reservation": false,
      "visitcount": 1364,
      "number": 19,
      "main": "한산소곡주",
      "content": "한산소곡주명인 농업회사법인(주) 최영숙 대표는 한산소곡주 이수자로 충청남도 무형문화재 3호인 古김영신 여사의 손부로 현재는 시어머니이신 우희열 명인(한국식품명인 19호)과 남편(전수자:나장연)함께 한산소곡주 공장을 운영해오고 있으며 4대를 이어 한산소곡주의 전통계승과 국내 농산물 소비를 향상을 위해 많은 노력을 기울이고 있으며 국내 전통주 산업의 향후 발전 방향과 안정적 매출 확대를 위해 노력하고 있습니다.",
      "activity": [
        {
          "activityLink": "https://www.sogokju.co.kr/notice",
          "title": "한산소곡주빚기",
          "description": "명인 한산 소곡주 빚기 시현 및 체험행사",
          "price": "150,000"
        }
      ],
      "mainImage": "https://modo-phinf.pstatic.net/20170122_79/1485066214321ua4e8_JPEG/mosadRYkzY.jpeg?type=f320_320"
    },
    {
      "title": "중원당",
      "location": "충북 충주시 가금면 창동리 243",
      "phone": "043-842-5005",
      "link": "http://www.청명주.com/",
      "alwaysvisit": false,
      "reservation": true,
      "visitcount": 1252,
      "number": 13,
      "main": "보은주, 호호, 써니10",
      "content": "충북 무형문화유산으로 지정된 청명주를 생산하는 양조장으로 충주에서 4대째 명맥을 이어 술을 빚고 있다",
      "activity": [
        {
          "activityLink": "https://www.sogokju.co.kr/notice",
          "title": "청명주 빚기 체험",
          "description": "양조장에서 생산산는 술을 시음하고 공장 견학을 한 뒤, 술빚기/누룩 빚기등을 체험함",
          "price": "35,000"
        }
      ],
      "mainImage": "https://modo-phinf.pstatic.net/20170122_79/1485066214321ua4e8_JPEG/mosadRYkzY.jpeg?type=f320_320"
    },
    {
      "title": "대강양조장",
      "location": "충북 단양군 대강면 대강로 60",
      "phone": "043-422-0077",
      "link": "http://www.krwine.com",
      "alwaysvisit": true,
      "reservation": false,
      "visitcount": 1330,
      "number": 14,
      "main": "생막걸리, 검은콩 막걸리",
      "content": "발효시키는 과정에서 현대화 된 스테인리스 용기로는 대강 막걸리만의 맛을 냏 수 없다는걸 알기에 80년 된 항아리를 이용한 전통방식을 아직도 고집하고 있습니다.",
      "activity": [
        {
          "activityLink": "http://www.krwine.com/",
          "title": "대강양조장 막걸리빚기",
          "description": "",
          "price": "무료"
        }
      ],
      "mainImage": "https://img4.yna.co.kr/photo/yna/YH/2013/06/29/PYH2013062901190006400_P4.jpg"
    },
    {
      "title": "조은술 세종",
      "location": "충북 청주시 청원구 사천로18번길 5-2",
      "phone": "043-218-7689",
      "link": "http://www.joeunsulsj.co.kr",
      "alwaysvisit": false,
      "reservation": true,
      "visitcount": 1487,
      "number": 17,
      "main": "유기농 이도22, 세종 쌀 막걸리",
      "content": "조은술 세종은 창업 이래 우리 전통주인 막걸리, 약주, 증류식 소주 등을 전통방식으로 제조하면서 현대인의 입맛에 맞게끔 끊임없이 노력해왔습니다. 기본을 지키는 정도경영을 바탕으로 차별화된 제품전략, 지속적인 품질향상과 과학적인 생산관리로 주류문화를 선도하는 기업으로서 거듭나겠습니다.",
      "activity": [
        {
          "activityLink": "https://www.joeunsulsj.co.kr:5009/sub.php?code=03_brew020101",
          "title": "견학",
          "description": "공장 생산 라인 견학, 시음",
          "price": "15,000"
        },
        {
          "activityLink": "https://www.joeunsulsj.co.kr:5009/sub.php?code=03_brew020101",
          "title": "체험",
          "description": "전통주 강의, 막걸리 빚기, 시음",
          "price": "25,000"
        }
      ],
      "mainImage": "https://modo-phinf.pstatic.net/20170123_59/1485136323693tefM4_JPEG/mosa0z6Ds0.jpeg?type=w1100"
    },
    {
      "title": "이원양조장",
      "location": "충청북도 옥천군 이원면 묘목로 113",
      "phone": "043-732-2177",
      "link": "http://iwonwine.com/new/index.php",
      "alwaysvisit": true,
      "reservation": false,
      "visitcount": 1301,
      "number": 22,
      "main": "유기농 이도22, 세종 쌀 막걸리",
      "content": "조은술 세종은 창업 이래 우리 전통주인 막걸리, 약주, 증류식 소주 등을 전통방식으로 제조하면서 현대인의 입맛에 맞게끔 끊임없이 노력해왔습니다. 기본을 지키는 정도경영을 바탕으로 차별화된 제품전략, 지속적인 품질향상과 과학적인 생산관리로 주류문화를 선도하는 기업으로서 거듭나겠습니다.",
      "activity": [
        {
          "activityLink": "https://www.joeunsulsj.co.kr:5009/sub.php?code=03_brew020101",
          "title": "견학",
          "description": "공장 생산 라인 견학, 시음",
          "price": "15,000"
        },
        {
          "activityLink": "https://www.joeunsulsj.co.kr:5009/sub.php?code=03_brew020101",
          "title": "체험",
          "description": "전통주 강의, 막걸리 빚기, 시음",
          "price": "25,000"
        }
      ],
      "mainImage": "https://san.chosun.com/news/photo/202102/14666_61440_3239.jpg"
    },
    {
      "title": "여포와인농장",
      "location": "충북 영동군 양강면 유점지촌길 75",
      "phone": "043-744-7702",
      "link": "https://yeopo.modoo.at/",
      "alwaysvisit": true,
      "reservation": false,
      "visitcount": 899,
      "number": 23,
      "main": "여포의 꿈 화이트",
      "content": "2018 평창올림픽, 2023 CITTA DEL VINO 등 국내외에서 수상하며, ‘인정받는 술을 만들자’라는 저희의 꿈은 이루어졌습니다. 이제는 여러분의 꿈을 응원하기 위해 술을 빚고 있습니다.",
      "activity": [
        {
          "activityLink": "https://www.joeunsulsj.co.kr:5009/sub.php?code=03_brew020101",
          "title": "와인 만들기 체험",
          "description": "간단히 만들어보는 나만의 와인, 제철에 수확된 포도를 직접 손질하여원하는 스타일의 와인을 만든다.",
          "price": "30,000"
        },
        {
          "activityLink": "https://www.joeunsulsj.co.kr:5009/sub.php?code=03_brew020101",
          "title": "와인 시음",
          "description": "여포 와인 농장의 와인을 시음하실 수 있는 프로그램양조 기간 별, 공정 전후 와인들을 시음하며, 맛과 향의 차이에 대한 강의를 듣는다.",
          "price": "10,000"
        }
      ],
      "mainImage": "https://d38cxpfv0ljg7q.cloudfront.net/admin_contents/origin/7CER-1634779043298-%EC%97%AC%ED%8F%AC%EC%99%80%EC%9D%B8%EB%86%8D%EC%9E%A5.png"
    },
    {
      "title": "시나브로 와이너리",
      "location": "충청북도 영동군 심천면 약목2길 23",
      "phone": "043-742-5275",
      "link": "https://www.bhwinery.com/index",
      "alwaysvisit": true,
      "reservation": true,
      "visitcount": 1023,
      "number": 25,
      "main": "시나브로 청수 화이트",
      "content": "소믈리에 가족”이 “HACCP인증받은 와이너리”에서 “우리나라 포도 품종”으로 만드는 “가장 한국적인”와인, 시나브로",
      "activity": [
        {
          "activityLink": "http://www.bhwinery.com/experience",
          "title": "나만의 와인 만들기",
          "description": "포도 수확후 포도를 제경 ,파쇄하여 효모를 접종한후 용기에 담아 준 후 집에서 1차, 2차 발효를 거치고 앙금 거르고 숙성시킨다. 3개월 후 취향에 맞게 나만의 와인이 탄생 한다",
          "price": "20,000"
        },
        {
          "activityLink": "http://www.bhwinery.com/experience",
          "title": "뱅쇼/상그리아 만들기",
          "description": "환절기에 목감기에 좋은 프랑스식 감기약 뱅쇼를, 여름청엔 싱그럽게 상큼한 상그리아를 만들어 시음해본다",
          "price": "15,000"
        },
        {
          "activityLink": "http://www.bhwinery.com/experience",
          "title": "와인족욕",
          "description": "온족욕,냉족욕에 와인을 넣어 스트레스를 날려 버리고 혈액순환에 도움이되는 힐링 타임",
          "price": "무료"
        }
      ],
      "mainImage": "https://d38cxpfv0ljg7q.cloudfront.net/content_images/contents_images-1622701622580-1.png"
    },
    {
      "title": "도란원",
      "location": "충청북도 영동군 매곡면 옥전리 825-1",
      "phone": "043-743-2109",
      "link": "http://xn--hg3b13gpoq4muubvz4a.kr/",
      "alwaysvisit": true,
      "reservation": false,
      "visitcount": 1309,
      "number": 24,
      "main": "샤토미소 로제스위트",
      "content": "대한민국 우리 술 품평회 과실주 대상 2회 수상, 아시아 와인 트로피 7연속 메달 수상, 대한민국 주류 대상 6연속 대상 수상, 2022년 대통령 취임식 만찬주 등 화려한 수상 경력을 갖고 있습니다. 가족이 함께 운영하고 있으며, 브랜드 샤토미소의 이름처럼 사람들의 미소와 함께 한 잔의 감동으로 기쁨의 미소를 드리고 싶은 샤토미소와인입니다.",
      "activity": [
        {
          "activityLink": "https://www.joeunsulsj.co.kr:5009/sub.php?code=03_brew020101",
          "title": "와인체험",
          "description": "와이너리 견학 및 도란원 와인 테이스팅 5종 이상",
          "price": "20,000"
        },
        {
          "activityLink": "https://www.joeunsulsj.co.kr:5009/sub.php?code=03_brew020101",
          "title": "와인족욕",
          "description": "와이너리 견학 및 와인테이스팅. 와인의 풍부한 비타민 유기산이 혈액순환을 원활하게 하여 피로감을 줄이고 피부미용을 돕는 족욕체험",
          "price": "20,000"
        },
        {
          "activityLink": "https://www.joeunsulsj.co.kr:5009/sub.php?code=03_brew020101",
          "title": "와인만들기",
          "description": "와이너리 견학 및 테이스팅. 포도를 이용한 와인 만들기.(포도 2kg, 용기 및 재료 포함 비용입니다)",
          "price": "40,000"
        }
      ],
      "mainImage": "https://샤토미소와인.kr/web/product/extra/big/20221017/1ac37b1b6ff97ae0917b1da557f41dd2.jpg"
    },
    {
      "title": "태인합동주조장",
      "location": "전북 정읍시 태인면 태흥리 392-1",
      "phone": "063-534-4018",
      "link": "http://www.태인양조장.com/",
      "alwaysvisit": false,
      "reservation": true,
      "visitcount": 1070,
      "number": 39,
      "main": "송명섭생막걸리",
      "content": "술은 문화니까 같이 향유할 때 그 보람과 가치가 더욱 커진다는 생각으로 술 제조 비법을 듣고자 하는 사람에게는 모든 정보를 공개하고 있습니다. 프랑스의 와인이나 영국의 위스키, 독일의 맥주는 모두 그 나라 고유의 식생활 문화를 반영하고 있습니다. 즉, 그 나라의 오랜 역사와 전통문화를 바탕으로 자국민의 사랑을 받았기에 세계적인 브랜드로 발돋움할 있었습니다. 「후한서 동이전」에 보면 우리 민족이 술과 함께 가무를 즐긴다고 기록돼 있듯 우리 민족의 음주문화는 단순히 마시고 취하는 것이 아닌 우리 민족의 멋과 풍류가 담긴 문화유산입니다. 앞으로도 태인합동주조는 문화유산을 계승하고 전통주의 저변확대를 위해 더욱 노력하겠습니다.",
      "activity": [
        {
          "activityLink": "http://www.xn--og5bv8a5dl6a612a.com/reservation/reservation.php",
          "title": "가향주 빚기",
          "description": "가향주를 손쉽게 가정집에서도 만들 수 있습니다.",
          "price": "400,000"
        },
        {
          "activityLink": "http://www.xn--og5bv8a5dl6a612a.com/reservation/reservation.php",
          "title": "누룩 만들기",
          "description": "막걸리의 기초인 누룩을 가정집에서 만들 수 있습니다.",
          "price": "400,000"
        },
        {
          "activityLink": "http://www.xn--og5bv8a5dl6a612a.com/reservation/reservation.php",
          "title": "가향주 만들기",
          "description": "옛 전통 방식 그대로 우리 술 빚어 보기",
          "price": "400,000"
        }
      ],
      "mainImage": "https://cdn.todayan.com/news/photo/201407/73370_54580_298.jpg"
    },
    {
      "title": "지리산 운봉주조",
      "location": "전북 남원시 운봉읍 서천리 622번지",
      "phone": "063-634-0009",
      "link": "http://www.herbsul.com/",
      "alwaysvisit": true,
      "reservation": true,
      "visitcount": 1376,
      "number": 42,
      "main": "지리산허브잎술 6%, 야관문 쌀막걸리 6%",
      "content": "지리산 해발 500ｍ의 지리산둘레길과 동편제 탯자리로 지리산에서 제일 높은곳에 위치한 주조장입니다. 30년의 전통과 2대째 전통주 제조의 자존심으로 오직 소비자를 생각 하는 자세로 안전한 막걸리를 만들기 위하여 위생적시설과 자동화 생산 시스템으로 좋은 술을 생산 하고 있습니다.",
      "activity": [],
      "mainImage": "https://mblogthumb-phinf.pstatic.net/MjAyMjAyMDhfMTM3/MDAxNjQ0MjkzNDgzNDE0.fAygkXoHyoGGrcsyC9BtB_Cm8oYmysVlUpteV6A5FZMg.zyjpFj_Jz7lYiTcQx5N5Vxm6vlwwWrSHPf1Uhi4D9Cog.JPEG.jbgokr/%EC%A0%9C%ED%92%881.jpg?type=w800"
    },
    {
      "title": "청산녹수",
      "location": "전남 장성군 장성읍 전고개로 240",
      "phone": "061-393-4141",
      "link": "http://www.bluegreenkorea.co.kr",
      "alwaysvisit": true,
      "reservation": false,
      "visitcount": 1337,
      "number": 40,
      "main": "편백숲산소막걸리",
      "content": "'양조는 과학입니다’ 산 좋고 물 맑은 전라남도 장성에 위치한 (주)청산녹수는 ‘과학으로 전통을 계승하는 양조장’이라는 슬로건답게 미생물 공학 박사 김진만 대표를 중심으로 2008년부터 운영되고 있다. 실험을 통해 누룩에서 술의 향미를 좋게하는 미생물을 선발·배양하고 특허받은 청산녹수만의 산소 발효 공법 등 ‘미생물 과학’을 양조에 적용하여 전통주를 빚고 있다.",
      "activity": [
        {
          "activityLink": "https://thesooltourism.com/reservation/input.do",
          "title": "견학/시음",
          "description": "양조장을 둘러보며 전통주가 빚어지는 과정에 대해 설명을 듣고, 청산녹수 대표막걸리 3종 (6.5도, 9도, 12도 막걸리 원액)을 시음해 보는 구성입니다.",
          "price": "30,000"
        },
        {
          "activityLink": "https://thesooltourism.com/reservation/input.do",
          "title": "술 내리기 체험+내린술 1병",
          "description": "양조장을 둘러보며 전통주가 빚어지는 과정에 대해 설명을 듣고, 직접 막걸리를 내리고 시음해 보는 구성입니다. 직접 내린 술을 가져갈 수 있도록 공병을 준비해 드립니다.",
          "price": "50,000"
        }
      ],
      "mainImage": "https://lh5.googleusercontent.com/proxy/ZeHunqpcHmIirjdnhOmoju0p0_oplG-qfj8jxP55TNy0anG8Vn6X-qsamPpBOnv2ZaAprnWF5uvTW7tz3l7EyxuEXbZHr0BEHdFdCieDgNR2NF9Sw2dryhoEPg"
    },
    {
      "title": "추성고을",
      "location": "전남 담양군 용면 추령로 29",
      "phone": "061-383-3011",
      "link": "http://www.chusungju.co.kr",
      "alwaysvisit": false,
      "reservation": true,
      "visitcount": 1558,
      "number": 41,
      "main": "추성주, 대잎술, 대통대잎술, 타미앙스, 죽력고",
      "content": "일천년의 맥을 이어온 전통주 추성주를 제조하고 있는 4대를 이어온 양조장으로 대한민국식품명인 제22호로 지정되어 꾸준한 전통주 발전의 연구개발을 통한 전통주의 가치를 높이면서 젊은층과 소통하는 양조장이 되도록 노력하고 있습니다.",
      "activity": [
        {
          "activityLink": "https://thesooltourism.com/reservation/input.do",
          "title": "나만의 증류주 만들기",
          "description": "전통소줏고리를 통한 전통방법의 증류주 내리기 체험&시음, 명인 또는 전수자와의 전통주 이야기, 체험객 기호에 맞는 나만의 증류주 만들기",
          "price": "25,000"
        }
      ],
      "mainImage": "https://modo-phinf.pstatic.net/20170124_236/1485243266890F0SKU_JPEG/mosa3t6563.jpeg?type=w1100"
    },
    {
      "title": "대대로영농조합법인",
      "location": "전남 진도군 군내면 둔전리 98",
      "phone": "061-542-3399",
      "link": "http://www.e-hongju.co.kr",
      "alwaysvisit": true,
      "reservation": false,
      "visitcount": 1279,
      "number": 43,
      "main": "진도홍주",
      "content": "일천년의 맥을 이어온 전통주 추성주를 제조하고 있는 4대를 이어온 양조장으로 대한민국식품명인 제22호로 지정되어 꾸준한 전통주 발전의 연구개발을 통한 전통주의 가치를 높이면서 젊은층과 소통하는 양조장이 되도록 노력하고 있습니다.",
      "activity": [
        {
          "activityLink": "https://thesooltourism.com/reservation/input.do",
          "title": "대대로영농조합법인 전통주 체험",
          "description": "",
          "price": "무료"
        }
      ],
      "mainImage": "https://lh4.googleusercontent.com/proxy/iI8xi1vVr3QaqR7uxi1xaZ30nTVTHJLQR54TrMpftdFYxz63Rpduzrct102Atonw_PIJl0tvFmbgXbKWPocNS62__HzArjEpH4npz7fgbqBfPp69VeInNUgv1w"
    },
    {
      "title": "해창주조장",
      "location": "전남 해남군 화산면 해창길 1",
      "phone": "061-532-5152",
      "link": "https://haechangjujo.modoo.at/",
      "alwaysvisit": true,
      "reservation": false,
      "visitcount": 1158,
      "number": 44,
      "main": "해창12도 찹쌀 생막걸리",
      "content": "땅끝 해남에 위치한 해창주조장은 최상급 멥쌀과 유기농 찹쌀로 무감미료 프리미엄 막걸리를 생산하고 있으며, 정원이 아름다운 주조장으로도 유명하다.",
      "activity": [
        {
          "activityLink": "https://thesooltourism.com/reservation/input.do",
          "title": "무료 시음체험 정원 관람",
          "description": "대표 상품 무료 시음 가능, 일본식 정원 관람",
          "price": "무료"
        }
      ],
      "mainImage": "https://lh3.googleusercontent.com/proxy/xu135W2U3S8oIvjrTVoGVwOVaLkM8fc_4_x50CcZ7viI0FFnOB7CuKAIG5KYdcDxr16vLwlazSyDwFrotC-lD4RS5jig1xJy9Xl-EA7STKiKb86yoDnDexvTozqTWSTK"
    },
    {
      "title": "예술주조",
      "location": "강원도 춘천시 신동면 풍류1길 6-3",
      "phone": 332611525,
      "link": "http://www.ye-sul.co.kr",
      "alwaysvisit": true,
      "reservation": true,
      "visitcount": 1453,
      "number": 10,
      "main": "해창12도 찹쌀 생막걸리",
      "content": "땅끝 해남에 위치한 해창주조장은 최상급 멥쌀과 유기농 찹쌀로 무감미료 프리미엄 막걸리를 생산하고 있으며, 정원이 아름다운 주조장으로도 유명하다.",
      "activity": [
        {
          "activityLink": "https://thesooltourism.com/reservation/input.do",
          "title": "양온소 예술 시음 티켓",
          "description": "예술술 3가지 테이스팅 및 전통주에 대한 간단한 소개 및 우리술 이야기를 들으며 양온소 돌아보기 (누룩건조실, 소주숙성실, 외관)",
          "price": "15,000"
        },
        {
          "activityLink": "https://thesooltourism.com/reservation/input.do",
          "title": "소주내리기",
          "description": "전통소주에 대한 강의 및 시음 - 소주고리에서 소주를 내린 후 개인당 100ml(알코올도수 60% 정도)를 가져갑니다. 전통소주의 우수성을 몸소 체험할 수 있습니다.",
          "price": "60,000"
        },
        {
          "activityLink": "https://thesooltourism.com/reservation/input.do",
          "title": "모주만들기",
          "description": "모주에 대한 강의 및 시음 - 모주(母酒)는 막걸리 앙금에 생강, 감초, 갈근, 대추, 계피등 5가지 약재로 달인 술로서 알코올 도수가 거의 없는 약술입니다. 모주내리기 체험 후에 개인당 1.5ℓ상당의 모주를 가져갑니다.",
          "price": "60,000"
        },
        {
          "activityLink": "https://thesooltourism.com/reservation/input.do",
          "title": "전통주 빚기 체험",
          "description": "전통술 빚기에 대한 강의 및 시음 - 전통누룩으로 빚어보는 우리 전통주",
          "price": "60,000"
        }
      ],
      "mainImage": "https://lh5.googleusercontent.com/proxy/RS72pouCnCsjB46Uzj7WV0A265196ty2zTWpCZno82lzt99JY2RSqY7HO9pIBxPliw"
    },
    {
      "title": "국순당",
      "location": "강원특별자치도 횡성군 둔내면 강변로 975",
      "phone": "033-340-4300",
      "link": "http://drink.ksdb.co.kr/",
      "alwaysvisit": false,
      "reservation": true,
      "visitcount": 1835,
      "number": 11,
      "main": "백세주, 국순당 먹걸리",
      "content": "국순당에서 운영하는 '주향로(술 향기 가득한 길)'에 오시면, 국내 최대 규모의 전통주 양조장을 견학하며 우리술의 역사와 문화를 체험하는 좋은 추억을 간직하실 수 있습니다.",
      "activity": [
        {
          "activityLink": "http://drink.ksdb.co.kr/brand/reservation.asp",
          "title": "국순당 주향로 견학",
          "description": "우리술 역사와 진실, 그리고 우리술이 만들어지는 과정을 '영상'으로 만날 수 있으며, 우리술 관련 전시물과 생산과정을 관람, 및 다양한 술을 시음할 수 있습니다.",
          "price": "무료"
        }
      ],
      "mainImage": "https://lh5.googleusercontent.com/proxy/RS72pouCnCsjB46Uzj7WV0A265196ty2zTWpCZno82lzt99JY2RSqY7HO9pIBxPliw"
    },
    {
      "title": "울진술도가",
      "location": "경상북도 울진군 근남면 노음2길 4",
      "phone": "054-782-1855",
      "link": false,
      "alwaysvisit": true,
      "reservation": true,
      "visitcount": 1313,
      "number": 29,
      "main": "왕피천을 품은 미소생막걸리, 미소 생막걸리",
      "content": "국순당에서 운영하는 '주향로(술 향기 가득한 길)'에 오시면, 국내 최대 규모의 전통주 양조장을 견학하며 우리술의 역사와 문화를 체험하는 좋은 추억을 간직하실 수 있습니다.",
      "activity": [
        {
          "activityLink": "https://thesool.com/front/visitingBrewery/M000000072/view.do?brewId=BR00000061",
          "title": "술 짜기 및 시음",
          "description": "물과 희석하지 않은 발효된 막거리 원주를 채에 걸러 직접 짜보는 체험 - 가장 신선한 막걸리를 마셔보고 만져볼 수 있다.",
          "price": "무료"
        }
      ],
      "mainImage": "https://lh5.googleusercontent.com/proxy/RS72pouCnCsjB46Uzj7WV0A265196ty2zTWpCZno82lzt99JY2RSqY7HO9pIBxPliw"
    },
    {
      "title": "오미나라",
      "location": "경북 문경시 문경읍 새재로 609",
      "phone": "054-572-0601",
      "link": "http://www.omynara.com/",
      "alwaysvisit": true,
      "reservation": false,
      "visitcount": 1114,
      "number": 27,
      "main": "오미로제 결, 고운달",
      "content": "오미나라는 경북 문경새재 초입에 자리하고 있으며, 우리나라가 원산지인 오미자를 원료로 와인과 증류주를 제조하고 문경 사과를 원료로 사과 증류주를 제조하는 양조장입니다.",
      "activity": [
        {
          "activityLink": "https://omynara.com/omynaratour/",
          "title": "와이너리투어 및 테이스팅 체험",
          "description": "해설자의 안내로 와인/증류주 제조시설을 관람하고 오미나라에서 생산하고 있는 와인과 증류주를 테이스팅 할 수 있는 체험 프로그램입니다.",
          "price": "10,000"
        },
        {
          "activityLink": "https://omynara.com/omynaratour/",
          "title": "나만의 기념주 만들기체험",
          "description": "와인/증류주 제조시설을 관람한 후, 나만의 라벨 제작용 사진을 촬영하고, 나만의 기념주(사과 증류주(40% Alc))를 만들어 가지고 가는 체험 프로그램입니다.",
          "price": "30,000"
        },
        {
          "activityLink": "https://omynara.com/omynaratour/",
          "title": "와이너리투어 및 테이스팅 체험",
          "description": "해설자의 안내로 와인/증류주 제조시설을 관람하고 오미나라에서 생산하고 있는 와인과 증류주를 테이스팅 할 수 있는 체험 프로그램입니다.",
          "price": "20,000"
        }
      ],
      "mainImage": "https://www.omynara.com/wp-content/uploads/2017/08/%EC%9D%B4%EC%A2%85%EA%B8%B0%EA%B5%90%EC%88%98.jpg"
    },
    {
      "title": "문경주조",
      "location": "경상북도 문경시 동로면 노은리 192번지",
      "phone": "054-552-8285",
      "link": "https://mgomijasul.modoo.at/",
      "alwaysvisit": true,
      "reservation": false,
      "visitcount": 1634,
      "number": 26,
      "main": "탁주",
      "content": "지역의 훌륭한 농,특산물을 활용하여 다양한 전통주를 만드는 양조장입니다.",
      "activity": [
        {
          "activityLink": "https://omynara.com/omynaratour/",
          "title": "시음",
          "description": "양조장에서 생산하는 다양한 제품들을 시음하며, 우리술에 관한 이야기를 할 수 있는 프로그램입니다.",
          "price": "10,000"
        },
        {
          "activityLink": "https://omynara.com/omynaratour/",
          "title": "전통주 빚기 체험",
          "description": "인공감미료가 첨가되지 않은, 우리 전통의 술을 직접 빚어 보고, 직접만든 술을 가져갈수 있는 전통주 빚기 체험입니다.",
          "price": "35,000"
        }
      ],
      "mainImage": "https://d38cxpfv0ljg7q.cloudfront.net/content_images/contents_images-1622733262329-%EB%AC%B8%EA%B2%BD1.png"
    },
    {
      "title": "명인안동소주",
      "location": "경북 안동시 풍산읍 산업단지6길 6",
      "phone": "054-856-6903",
      "link": "http://www.adsoju.com",
      "alwaysvisit": true,
      "reservation": false,
      "visitcount": 1862,
      "number": 28,
      "main": "명인안동소주",
      "content": "우리나라 역사가 묻어있는 유일한 명가의 술 입니다. 안동소주가 700여년전 고려시대에 처음 우리나라에 전해지면서 역사가 시작되었고, 안동의 명문가인 반남박씨의 가양주로 500년의 전통을 이어온 안동소주를 반남박씨 25대손인 박재서 명인께서 역사와 정통성을 그대로 이어 만든 오리지날 안동소주로서 자존심과 자부심을 느낍니다.",
      "activity": [
        {
          "activityLink": "http://www.adsoju.com/",
          "title": "시음 및 전시관 관람",
          "description": "명인안동소주 시음, 영상 및 전시시설 관람",
          "price": "무료"
        },
        {
          "activityLink": "http://www.adsoju.com/",
          "title": "칵테일 체험",
          "description": "안동소주를 이용한 다양한 칵테일 직접 만들기",
          "price": "무료"
        },
        {
          "activityLink": "http://www.adsoju.com/",
          "title": "전통주 빚기",
          "description": "누룩 만드는 과정 및 누룩 틀 밟기 체험",
          "price": "20,000"
        }
      ],
      "mainImage": "https://cdn.sommeliertimes.com/news/photo/201703/4385_8185_5213.jpg"
    },
    {
      "title": "한국애플리즈",
      "location": "경북 의성군 단촌면 일직점곡로 755",
      "phone": "054-834-7800",
      "link": "http://www.applewine.co.kr/",
      "alwaysvisit": true,
      "reservation": false,
      "visitcount": 860,
      "number": 32,
      "main": "사과와인, 사이더",
      "content": "경북 의성에서 재배한 사과로 사과와인을 제조하는 대표 기업",
      "activity": [
        {
          "activityLink": "https://thesooltourism.com/reservation/input.do",
          "title": "양조장 투어",
          "description": "양조장 투어 및 시음",
          "price": "15,000"
        }
      ],
      "mainImage": "https://lh6.googleusercontent.com/proxy/ORCmEJDy_abhOg9haSgW8nvf087g9viPcvqEX4uAl6lByVQtaE9zAq7B25E5Tmx9lARL5J74zAGj2irSKU_aPND84sI-AY9QV9fTdYsoRd37kA0mN_N25IoBq_E"
    },
    {
      "title": "은척양조장",
      "location": "경북 상주시 은척면 봉중2길 16-4",
      "phone": "054-541-6409",
      "link": "https://takbaeki.modoo.at/",
      "alwaysvisit": true,
      "reservation": false,
      "visitcount": 937,
      "number": 30,
      "main": "은자골 생 탁배기 5%",
      "content": "3대째 이어지고 있는 발효실과 백 년이 넘은 술독이 아직도 현역으로 제 몸을 비우고 채우는 일을 계속하고 있습니다. 은척 양조장의 생 탁배기는 상주지역 햇 상주삼백쌀과 전통누룩을 원료로 하여 빚은 막걸리로, 쌀 막걸리 특유의 부드러운 목넘김을 가지고 있으며 청량감이 일품입니다.",
      "activity": [],
      "mainImage": "https://lh5.googleusercontent.com/proxy/UlAuS6Q45PIw-f7VRhVNCCa1BMwJA_FhfUX775DYE8WNr-k8qrir4HYGqS_OxZ3IUEu-g25DG4AEPLbaNiJOgJjrzHUDCkEfXhigQVyRkjT-KFW9s9uKvp-yRg"
    },
    {
      "title": "한국와인",
      "location": "경상북도 영천시 금호읍 원기리 414-2",
      "phone": "054-333-3010",
      "link": "http://www.vincoreewinery.com/",
      "alwaysvisit": true,
      "reservation": false,
      "visitcount": 885,
      "number": 33,
      "main": "뱅꼬레 화이트, 뱅꼬레 로제",
      "content": "Vin은 프랑스어로 된 와인이고 Coree는 한국입니다. 국내 최대 과일의 고장 영천에서 나는 좋은 과일로 만든 최고의 와인,저희는 가장 유력한 한국산 글로벌 와인을 만든다는 자부심을 가지고브랜드를 유지하기 위해 최선을 다할 것입니다.",
      "activity": [
        {
          "activityLink": "https://www.vincoreewinery.com/36",
          "title": "와인 만들기 체험",
          "description": "",
          "price": "무료"
        }
      ],
      "mainImage": "https://pimg.mk.co.kr/meet/neds/2019/01/image_readtop_2019_16409_15469812623597073.jpg"
    },
    {
      "title": "고도리 와이너리",
      "location": "경북 영천시 고경면 고도길 38",
      "phone": "054-335-3174",
      "link": "http://고도리와인.com",
      "alwaysvisit": true,
      "reservation": false,
      "visitcount": 1658,
      "number": 34,
      "main": "고도리 레드자두와인",
      "content": "지역 와인사업의 선발주자로써 자체 포도재배에서부터 모든 과정을 엄격히 관리하며 한결같은 안전의 원칙에 따라 '한국사람들이 사랑하는 와인'을 만들자는 신념으로 와인사업을 하고 있습니다. 차별화된 와인을 만들려는 노력과 연구 끝에 톡톡 입안에서 터져 나오는 스파클링한 느낌을 주는 와인을 개발하여 소비자로부터 사랑받는 와인을 만들기 위해 꾸준히 노력하겠습니다.",
      "activity": [],
      "mainImage": "https://cdn.kbanker.co.kr/news/photo/202211/207295_56073_3553.jpg"
    },
    {
      "title": "수도산와이너리",
      "location": "경상북도 김천시 증산면 금곡리 226-1번지",
      "phone": "054-439-1518",
      "link": "https://smartstore.naver.com/sdsmeru/profile",
      "alwaysvisit": true,
      "reservation": true,
      "visitcount": 911,
      "number": 31,
      "main": "수도산와이너리 크라테 산머루주 국산 레드와인 드라이",
      "content": "김천 수도산 와이너리의 크라테 와인은 한국의 '아마로네'라는 찬사를 받은 와인입니다. 이탈리아 베네토 지역에서는 포도를 수확한 다음 건조시켜 당분을 끌어올린 다음 와인을 만드는데요. 수도산 와이너리는 산머루 수확을 늦게 하여 건조한 다음 와인을 만들고 있습니다.",
      "activity": [],
      "mainImage": "https://d38cxpfv0ljg7q.cloudfront.net/content_images/contents_images-1622687305865-1.jpg"
    },
    {
      "title": "복순도가",
      "location": "울산광역시 울주군 상북면 향산리 439",
      "phone": "1577-6746",
      "link": "http://www.boksoon.com/",
      "alwaysvisit": true,
      "reservation": false,
      "visitcount": 1904,
      "number": 38,
      "main": "복순도가 막걸리",
      "content": "어머니의 마음으로 정성스러운 막걸리를 만드는 것, 바로 복순도가의 신념입니다. 항상 좋은 것만 주시려는 어머니의 마음을 따라 국산 쌀만을 사용하여 전통 방식 그대로 옛 항아리에 담아 빚었습니다. 살아 숨 쉬는 누룩이 만들어낸 천연 탄산은 긴 발효의 기다림이 주는 선물입니다.",
      "activity": [
        {
          "activityLink": "https://barhyo-village.com/Class",
          "title": "365발효마을 발효로드 프로그램",
          "description": "발효의 과정을 직접 연구하고 체험하여 나만의 ‘발효제품’ 및 ‘콘텐츠’를 만들어갑니다.",
          "price": "무료"
        }
      ],
      "mainImage": "https://m.segye.com/content/image/2020/12/01/20201201509134.jpg"
    },
    {
      "title": "금정산성 토산주",
      "location": "부산 금정구 산성로 453",
      "phone": "051-517-6552",
      "link": "http://www.sanmak.kr/",
      "alwaysvisit": true,
      "reservation": false,
      "visitcount": 1432,
      "number": 37,
      "main": "금정산성막걸리",
      "content": "부산의 대표 전통주 금정산성토산주 유청길 대표는 농림축산식품부로부터 2013년 12월 3일 대한민국 최초 막걸리분야 식품 명인으로 지정받았습니다. 해발 400m인 금정산 기슭의 기후와 맑은 물, 500년 전통의 족타식 누룩을 직접 만들어 금정산성막걸리를 제조하고 있습니다.",
      "activity": [
        {
          "activityLink": "https://sanmak.kr/bbs/content.php?co_id=sub31",
          "title": "누룩 딛기 체험",
          "description": "누룩 딛기 체험",
          "price": "10,000"
        },
        {
          "activityLink": "https://sanmak.kr/bbs/content.php?co_id=sub31",
          "title": "막걸리 빚기 체험",
          "description": "막걸리 빚기 체험",
          "price": "20,000"
        },
        {
          "activityLink": "https://sanmak.kr/bbs/content.php?co_id=sub31",
          "title": "막걸리 거르기 체험",
          "description": "막걸리 거르기 체험",
          "price": "15,000"
        },
        {
          "activityLink": "https://sanmak.kr/bbs/content.php?co_id=sub31",
          "title": "막걸리 빚기와 막걸리 거르기 체험",
          "description": "막걸리 빚기와 막걸리 거르기 체험",
          "price": "35,000"
        },
        {
          "activityLink": "https://sanmak.kr/bbs/content.php?co_id=sub31",
          "title": "누룩 딛기와 막걸리 빚기, 거르기 체험",
          "description": "누룩 딛기와 막걸리 빚기, 거르기 체험",
          "price": "45,000"
        }
      ],
      "mainImage": "https://db.kookje.co.kr/news2000/photo/2017/0705/20170705.22024193640i2.jpg"
    },
    {
      "title": "제주샘주",
      "location": "제주 제주시 애월읍 애원로 283",
      "phone": "064-799-4225",
      "link": "http://www.jejusaemju.co.kr",
      "alwaysvisit": true,
      "reservation": false,
      "visitcount": 1110,
      "number": 45,
      "main": "고소리술, 오메기술",
      "content": "국내는 물론 세계에서도 인정받은 명실상부 대한민국 명주로 더욱 발전해 나가고 있습니다. 앞으로도 '온 정성을 다하여 모든이에게 이로운 술'이 되자라는 사훈아래 모든 직원이 힘을 모아 명품주를 생산하는 제주샘酒가 되겠습니다. 제주샘영농조합법인 제주샘酒",
      "activity": [
        {
          "activityLink": "https://jejusaemju.co.kr/experience",
          "title": "오메기떡 체험",
          "description": "‘오메기술’이란 예로부터 ‘오메기떡’을 삶아 건져 낸 후 누룩과 함께 으깨어 발효시킨 술로 ‘오메기술’을 만들기 위해서는 ‘오메기떡’을 기본 원료로 사용하여 만든다. ‘오메기술’을 이해하기 위해서는 ‘오메기떡’을 직접 빚어보는 것이 최고의 방법 중 하나다. 허나, 지금 체험하는 ‘오메기떡’은 현대인의 입맛에 맞도록 변형된 떡이다.",
          "price": "30,000"
        },
        {
          "activityLink": "https://jejusaemju.co.kr/experience",
          "title": "쉰다리 체험",
          "description": "‘쉰다리’는 여름철 제주도 사람들이 먹다가 남은 밥이 쉬어버리면 버리지 않고 물로 한번 헹구어서 누룩과 함께 섞어 발효를 시켜 만든 음료입니다. 제주도 선조들의 알뜰함을 보여주는 음식으로 여름철 남녀노소 구분 없이 즐겨 마셨던 음료입니다. ‘쉰다리’는 새콤하고 달콤한 맛이 나며 누룩곰팡이와 쌀의 녹말과 어울려 유기산이 많은 음료로 서양의 요구르트와 비슷합니다.",
          "price": "30,000"
        },
        {
          "activityLink": "https://jejusaemju.co.kr/experience",
          "title": "칵테일 체험",
          "description": "제주샘酒의 ‘고소리술’을 이용하여 제주샘酒만의 칵테일 레시피에 따라 직접 칵테일을 만들어 보고 시음해 볼 수 있습니다.",
          "price": "30,000"
        }
      ],
      "mainImage": "https://cdn.imweb.me/upload/S2020040856eb2430e5a6d/487445d5c6d6c.jpeg"
    },
    {
      "title": "제주고소리술익는집",
      "location": "제주도 서귀포시 표선면 중산간동로 4726",
      "phone": "064-787-5046",
      "link": "http://jejugosorisul.com/",
      "alwaysvisit": true,
      "reservation": false,
      "visitcount": 1277,
      "number": 46,
      "main": "제주 고소리술",
      "content": "대한민국식품명인 제84호 제주특별자치도 무형문화재 제11호 김희숙 명인과 전수자들이 함께 모여, 제주도민의 애환이 깃들어 있는 제주의 술을 옛방식 그대로 빚고 있습니다.",
      "activity": [
        {
          "activityLink": "https://www.jejugosorisul.com/pages.php?p=4_1_1_1",
          "title": "누룩만들기 & 쉰다리빚기",
          "description": "전통방식의 누룩빚는 노하우를 식품명인으로부터 배워볼 수 있는 체험입니다.",
          "price": "40,000"
        }
      ],
      "mainImage": "https://img6.yna.co.kr/etc/inner/KR/2020/06/19/AKR20200619074000805_12_i_P4.jpg"
    },
    {
      "title": "모월",
      "location": "강원 원주시 판부면 판부신촌길 84",
      "phone": "033-748-8008",
      "link": "http://www.mowall.co.kr/",
      "alwaysvisit": false,
      "reservation": false,
      "visitcount": 1199,
      "number": 12,
      "main": "모월 인, 모월 로",
      "content": "협동조합 모월은 산 높고, 물 맑은 강원도 원주에 자리 잡은 전통주 양조장입니다. 끊어진 전통주의 맥을 잇고 올바른 술문화를 공부하고 후대에 바른 술문화를 교육하고자 뜻을 함께한 사람들이 모여 만든 양조장입니다.",
      "activity": [
        {
          "activityLink": "https://www.mowall.co.kr/experience-mowall/",
          "title": "2020년 대통령상 수상작 '모월인' 포함 4종 시음&양조장 견학",
          "description": "증류식 소주 양조 과정 강의 및 시음",
          "price": "30,000"
        }
      ],
      "mainImage": "https://www.mowall.co.kr/wp-content/uploads/2023/12/%EB%AA%A8%EC%9B%94_%ED%99%88%ED%8E%98%EC%9D%B4%EC%A7%80main_231218_37.jpg"
    },
    {
      "title": "술아원",
      "location": "경기 여주 점봉길 93-12",
      "phone": "070-8776-0043",
      "link": "http://soolawon.co.kr/",
      "alwaysvisit": false,
      "reservation": false,
      "visitcount": 1228,
      "number": 9,
      "main": "모월 인, 모월 로",
      "content": "협동조합 모월은 산 높고, 물 맑은 강원도 원주에 자리 잡은 전통주 양조장입니다. 끊어진 전통주의 맥을 잇고 올바른 술문화를 공부하고 후대에 바른 술문화를 교육하고자 뜻을 함께한 사람들이 모여 만든 양조장입니다.",
      "activity": [
        {
          "activityLink": "https://soolawon.co.kr/main/index",
          "title": "찹쌀 막걸리 빚기",
          "description": "증류식 소주 양조 과정 강의 및 시음",
          "price": "30,000"
        }
      ],
      "mainImage": "https://d38cxpfv0ljg7q.cloudfront.net/content_images/contents_images-1622706631613-%EC%88%A0%EC%95%84%EC%9B%901.png"
    },
    {
      "title": "장희도가",
      "location": "충북 청주 청원구 내수읍 미원초정로 1275",
      "phone": "070-4415-6567",
      "link": "https://jhdg3491.modoo.at/",
      "alwaysvisit": false,
      "reservation": false,
      "visitcount": 995,
      "number": 21,
      "main": "세종대왕어주 약주",
      "content": "협동조합 모월은 산 높고, 물 맑은 강원도 원주에 자리 잡은 전통주 양조장입니다. 끊어진 전통주의 맥을 잇고 올바른 술문화를 공부하고 후대에 바른 술문화를 교육하고자 뜻을 함께한 사람들이 모여 만든 양조장입니다.",
      "activity": [
        {
          "activityLink": "https://jhdg3491.modoo.at/?link=3cc8lwjg",
          "title": "딸기막걸리 만들기 체험",
          "description": "지역의 청원생명딸기 와 쌀를 이용하고 찹쌀 고두밥을 쩌서 차게 식힌 후 누룩을 넣어 혼합한 후 담은 술을 집에 가저가서 여과해서 드실 수있게 함.(세종대왕어주 약주, 탁주 시음)",
          "price": "30,000"
        },
        {
          "activityLink": "https://jhdg3491.modoo.at/?link=3cc8lwjg",
          "title": "막걸리 담아기기 체험",
          "description": "지역의 청원생명 쌀을 이용하고 찹쌀 고두밥을 쩌서 차게 식힌 후 누룩을 넣어 혼합한 후 담은 술을 집에 가저가서 여과해서 드실 수있게 함.(세종대왕어주 약주, 탁주 시음)",
          "price": "30,000"
        },
        {
          "activityLink": "https://jhdg3491.modoo.at/?link=3cc8lwjg",
          "title": "식초 음료 만들기 체험",
          "description": "천연발효식초를 활용한 음료 만들어 보기 체험",
          "price": "30,000"
        }
      ],
      "mainImage": "https://modo-phinf.pstatic.net/20220511_225/1652252723566LDe0i_JPEG/mosaBVJOmE.jpeg?type=f320_320"
    },
    {
      "title": "하미앙 와인밸리",
      "location": "경남 함양군 함양읍 삼봉로 442-14",
      "phone": "055-964-2500",
      "link": "https://www.sanmuru.com",
      "alwaysvisit": false,
      "reservation": true,
      "visitcount": 902,
      "number": 36,
      "main": "세종대왕어주 약주",
      "content": "협동조합 모월은 산 높고, 물 맑은 강원도 원주에 자리 잡은 전통주 양조장입니다. 끊어진 전통주의 맥을 잇고 올바른 술문화를 공부하고 후대에 바른 술문화를 교육하고자 뜻을 함께한 사람들이 모여 만든 양조장입니다.",
      "activity": [
        {
          "activityLink": "https://sanmuru.com/?page_id=321",
          "title": "와이너리투어",
          "description": "농장시설 견학 + 와인시음하기",
          "price": "무료"
        },
        {
          "activityLink": "https://sanmuru.com/?page_id=321",
          "title": "나만의 와인 만들기",
          "description": "주입되어 있는 와인병에 라벨을 붙여 가져가기",
          "price": "33,000"
        },
        {
          "activityLink": "https://sanmuru.com/?page_id=321",
          "title": "나만의 뱅쇼만들기",
          "description": "산머루 와인에 제철과일 및 향신료를 넣고 오래도록 끓여서 전통적인 유럽식 뱅쇼만들기 체험하기",
          "price": "37,000"
        }
      ],
      "mainImage": "https://www.ktsketch.co.kr/news/photo/202406/8063_42430_4830.jpg"
    },
    {
      "title": "풍정사계",
      "location": "충청북도 청주시 청원구 내수읍 풍정1길 8-2",
      "phone": "043-214-9424",
      "link": "https://www.hwayang.co/",
      "alwaysvisit": true,
      "reservation": true,
      "visitcount": 717,
      "number": 18,
      "main": "풍정사계(춘, 하, 추, 동)",
      "content": "협동조합 모월은 산 높고, 물 맑은 강원도 원주에 자리 잡은 전통주 양조장입니다. 끊어진 전통주의 맥을 잇고 올바른 술문화를 공부하고 후대에 바른 술문화를 교육하고자 뜻을 함께한 사람들이 모여 만든 양조장입니다.",
      "activity": [],
      "mainImage": "https://image.kmib.co.kr/online_image/2017/1107/611721110011883294_1.jpg"
    },
    {
      "title": "솔송주",
      "location": "경상남도 함양군 지곡면 지곡창촌길 3",
      "phone": "055-963-8992",
      "link": "https://www.solsongju.com/",
      "alwaysvisit": true,
      "reservation": false,
      "visitcount": 638,
      "number": 35,
      "main": "솔송주, 담솔 40",
      "content": "솔송주는 지리산에서 내려온 맑은 물, 청정한 공기, 인근 지역에서 자란 신선한 원료로 술을 빚습니다. (주)솔송주의 술은 자연이 인간에게 준 최고의 선물로 완성됩니다.",
      "activity": [
        {
          "activityLink": "https://www.solsongju.com/main/html.php?htmid=service/program_01.html",
          "title": "시음 및 술송주 문화관 관람",
          "description": "솔송주와 담솔 시음, 솔송주 문화관 내부 관람 가능, 시음을 원하시는 경우 안내 데스크에 말씀하시면 됩니다.",
          "price": "무료"
        },
        {
          "activityLink": "https://www.solsongju.com/main/html.php?htmid=service/program_01.html",
          "title": "칵테일 만들기",
          "description": "담솔 제품을 이용해 다양한 칵테일을 만들고 맛봅니다. 체험 시, 다과가 포함됩니다.",
          "price": "20,000"
        },
        {
          "activityLink": "https://www.solsongju.com/main/html.php?htmid=service/program_01.html",
          "title": "증류주 내리기 및 칵테일 만들기",
          "description": "소줏고리를 이용해 옛방식으로 증류주 내리는 모습을 관찰하고 맛과 향을 느껴봅니다.",
          "price": "30,000"
        }
      ],
      "mainImage": "https://dimg.donga.com/wps/NEWS/IMAGE/2009/12/10/24699588.2.jpg"
    },
    {
      "title": "금풍양조",
      "location": "인천 강화군 길상면 삼랑성길 8",
      "phone": "070-4400-1931",
      "link": "https://www.instagram.com/on_sul/",
      "alwaysvisit": false,
      "reservation": false,
      "visitcount": 767,
      "number": 47,
      "main": "금풍양조, 금학탁주",
      "content": "요거트에서 느껴질 법한 산뜻한 향과 누룩의 고소한 향을 갖고 있어요. 술을 머금으면 은은한 단맛과 시간이 지날수록 쓴맛이 올라오는 것도 느낄 수 있을 거예요. 또한, 질감이 묽은 만큼 목 넘김은 가벼운 편이에요.",
      "activity": [
        {
          "activityLink": "https://sanmuru.com/?page_id=321",
          "title": "막걸리를 만드는 사람들",
          "description": "막걸리빚기 체험(90') + 양조장투어(30')",
          "price": "50,000"
        },
        {
          "activityLink": "https://sanmuru.com/?page_id=321",
          "title": "길상술레길",
          "description": "[길상 술레길]막걸리 키트 셀프체험 및 양조장투어 (60')",
          "price": "30,000"
        },
        {
          "activityLink": "https://sanmuru.com/?page_id=321",
          "title": "금풍양조장투어",
          "description": "막걸리 시음 (30‘) 및 양조장 투어 (30’)",
          "price": "20,000"
        }
      ],
      "mainImage": "https://cdn.esgeconomy.com/news/photo/202205/2205_3169_4233.png"
    },
    {
      "title": "오산양조",
      "location": "경기도 오산시 중앙동 시장길 63",
      "phone": "031-374-2139",
      "link": "https://www.osansool.com/",
      "alwaysvisit": true,
      "reservation": true,
      "visitcount": 710,
      "number": 48,
      "main": "하얀까마귀, 독산 53",
      "content": "지역의 유•무형 자원을 적극적으로 활용하여 지역자원을 순환시키고, 다양한 문화행사를 통해 시민들과 소통하며, 오산의 발전에 기여하는 마을기업 / 오산양조(주)입니다.",
      "activity": [
        {
          "activityLink": "https://www.osansool.com/main/html.php?htmid=service/activity.html&myShop",
          "title": "전통주 빚기 체험",
          "description": "전통주 빚기 체험 프로그램으로, 3L 용기에 담아 가져가실 수 있습니다.(최소 8인 이상 진행 가능합니다)",
          "price": "30,000"
        },
        {
          "activityLink": "https://www.osansool.com/main/html.php?htmid=service/activity.html&myShop",
          "title": "이벤트 술 빚기",
          "description": "행사 기념, K-culture 체험, 이벤트용 술 빚기 체험 프로그램으로, 체험 내용은 협의 가능합니다.",
          "price": "300,000"
        },
        {
          "activityLink": "https://www.osansool.com/main/html.php?htmid=service/activity.html&myShop",
          "title": "견학 프로그램",
          "description": "양조장 소개와 시음, 현장 견학으로 진행되며, 최소 4인 이상 진행 가능합니다.",
          "price": "25,000"
        }
      ],
      "mainImage": "https://cdn.esgeconomy.com/news/photo/202205/2205_3169_4233.png"
    },
    {
      "title": "산막와이너리",
      "location": "충북 영동군 영동읍 산막골길 31-45",
      "phone": "043-745-3888",
      "link": "http://www.sanmacwine.com/web/main/",
      "alwaysvisit": true,
      "reservation": true,
      "visitcount": 598,
      "number": 49,
      "main": "하얀까마귀, 독산 53",
      "content": "지역의 유•무형 자원을 적극적으로 활용하여 지역자원을 순환시키고, 다양한 문화행사를 통해 시민들과 소통하며, 오산의 발전에 기여하는 마을기업 / 오산양조(주)입니다.",
      "activity": [
        {
          "activityLink": "https://sanmuru.com/?page_id=321",
          "title": "시음/투어/공연",
          "description": "산막와이너리의 대표와인시음, 포도밭과 와이너리 시설투어, 간단한 공연까지",
          "price": "25,000"
        },
        {
          "activityLink": "https://sanmuru.com/?page_id=321",
          "title": "수확체험",
          "description": "가을 수확철에만 이루어지는 포도수확체험, 수확후 즐거운 파티까지 그리고 본인의 사진으로 라벨링된 와인까지 획득",
          "price": "20,000"
        }
      ],
      "mainImage": "https://flexible.img.hani.co.kr/flexible/normal/970/728/imgdb/original/2021/0906/20210906503347.jpg"
    },
    {
      "title": "맑은내일",
      "location": "경남 창원시 삼귀로 411-8",
      "phone": "055-264-0996",
      "link": "https://www.good-tomorrow.co.kr/",
      "alwaysvisit": false,
      "reservation": true,
      "visitcount": 1067,
      "number": 50,
      "main": "맑은내일 발효 막걸리 시그니처 6.5%, 운암 1945",
      "content": "시간이 만든 제조기술력의 차이, 맑은 내일은 오랜시간 같은 길을 걸어온 우직한 힘을 믿습니다. 가장 좋은 원료를 구하기 위한 노력 그것을 잘 가공하는 제조기술력을 키우며 성장해왔습니다.",
      "activity": [],
      "mainImage": "https://dimg.donga.com/ugc/CDB/WEEKLY/Article/62/15/8e/38/62158e3812021e149ab.jpg"
    },
    {
      "title": "인천탁주",
      "location": "인천광역시 부평구 안남로 433번길 14",
      "phone": "032-524-5016",
      "link": "http://sosungju.modoo.at/",
      "alwaysvisit": false,
      "reservation": false,
      "visitcount": 277,
      "number": 51,
      "main": "인천생소성주",
      "content": "1990년 업계 최초로 쌀 막걸리를 출시한 인천탁주. 90년대 초부터 수출을 시작하고 92년 우수 포장선정 국세청장의 표창까지 받은 유서 깊은 양조으로, 인천지역 막걸리 시장의 큰손으로 자리매김하고 있다. 지난 1974년 인천지역의 11개 양조장의 합병으로 만들어져 72년간의 오랜 경험을 바탕으로 인천의 자부심을 가지고 막걸리를 빚고 있다.",
      "activity": [
        {
          "activityLink": "https://sosungju.modoo.at/?link=8oqmzb63",
          "title": "막걸리 빚기",
          "description": "투명단지에 직접 술을 빚어 담아가서 발효 과정을 매일 눈으로 볼 수 있습니다.",
          "price": "25,000"
        },
        {
          "activityLink": "https://sosungju.modoo.at/?link=8oqmzb63",
          "title": "나만의 증류주 만들기",
          "description": "증류의 기초 이론 교육 및 직접 증류를 경험할 수 있는 체험입니다.",
          "price": "30,000"
        },
        {
          "activityLink": "https://sosungju.modoo.at/?link=8oqmzb63",
          "title": "술지게미 비누 만들기",
          "description": "술지게미를 이용한 업사이클링, 수제 비누 만들기 체험입니다.",
          "price": "10,000"
        }
      ],
      "mainImage": "https://cdn.incheontoday.com/news/photo/201004/14445_11230_5239.jpg"
    },
    {
      "title": "술빚는 전가네",
      "location": "경기도 포천시 영북면 산정호수로 335",
      "phone": "050-71329-9708",
      "link": "https://www.sooldoga.com/home",
      "alwaysvisit": false,
      "reservation": false,
      "visitcount": 234,
      "number": 52,
      "main": "산정호수 동정춘 막걸리, 고향춘",
      "content": " 우리의 주조 방식은 오랜 세월 동안 전승되어 온 전통적인 방법에 기반을 두고 있습니다. 각각의 술은 자연 발효 과정을 거쳐, 고유의 맛과 향을 지닙니다. 이 고유성은 현대적인 제조 기술과의 조화를 통해 더욱 독특하고 매력적인 맛으로 탄생됩니다.",
      "activity": [
        {
          "activityLink": "https://sosungju.modoo.at/?link=8oqmzb63",
          "title": "찹쌀 단양주 빚기체험",
          "description": "찹쌀을 이용해서 전통 단양주 빚기체험",
          "price": "30,000"
        }
      ],
      "mainImage": "https://static.wixstatic.com/media/d122b9_fb0e7c1bfc5b4672a2066f61a13c1f0a~mv2.jpg/v1/crop/x_0,y_39,w_1536,h_1971/fill/w_526,h_706,al_c,q_85,usm_0.66_1.00_0.01,enc_auto/%EB%B0%98%EC%8B%A0.jpg"
    },
    {
      "title": "두레양조",
      "location": "충청남도 천안시 서북구 입장면 율목길 17-6",
      "phone": "041-585-8213",
      "link": "https://shopping.naver.com/fresh/traditionalalcohol/stores/100293334",
      "alwaysvisit": false,
      "reservation": false,
      "visitcount": 272,
      "number": 53,
      "main": "두레앙",
      "content": "천혜의 포도 재배지 천안에서 '두레앙 와인'을 생산하고 있습니다. '두레앙 와인'이 여러분의 삶에 작은 윤활유가 되기를 기대합니다.",
      "activity": [
        {
          "activityLink": "http://www.duraean.co.kr/sub/tourism.php",
          "title": "전체관람,교육",
          "description": "회사 소개 후 제품시음 및 교육, 술 자료 박물관 관람후 공장견학",
          "price": "20,000"
        }
      ],
      "mainImage": "https://thumbnews.nateimg.co.kr/view610///news.nateimg.co.kr/orgImg/ck/2021/01/24/kuk202101240075.680x.9.jpg"
    },
    {
      "title": "양촌감 와이너리",
      "location": "충청남도 논산시 양촌면 황산벌로 1075-21",
      "phone": "050-71466-8937",
      "link": "https://smartstore.naver.com/choosi/?NaPm=ct%3Dlkm6j0d2%7Cci%3Dcheckout%7Ctr%3Dds%7Ctrx%3Dnull%7Chk%3D1c05f130954f743bc8fb02b7bf901eade5a17fdc",
      "alwaysvisit": false,
      "reservation": false,
      "visitcount": 528,
      "number": 54,
      "main": "아치23, 추시 감와인",
      "content": "천혜의 포도 재배지 천안에서 '두레앙 와인'을 생산하고 있습니다. '두레앙 와인'이 여러분의 삶에 작은 윤활유가 되기를 기대합니다.",
      "activity": [
        {
          "activityLink": "https://booking.naver.com/booking/6/bizes/873941",
          "title": "체험관 운영",
          "description": "와인, 증류주 등 무료 시음/감 증류주를 베이스로 한 하이볼 제공(전통주 구매고객 한정)/시음주와 즐길 수 있는 간단한 스낵과 시음 공간 제공",
          "price": "미기재"
        },
        {
          "activityLink": "https://booking.naver.com/booking/6/bizes/873941",
          "title": "송어양식장과 연계한 특별 양조장 체험",
          "description": "지역특산주와 페어링한 송어요리 식사/카페에서 전통주 시음하며 휴식/양조체험으로 술 만들기/호수 수변길에서 산책/야외정원공간 및 연못에서 휴식",
          "price": "미기재"
        },
        {
          "activityLink": "https://booking.naver.com/booking/6/bizes/873941",
          "title": "와인 양조체험으로 술 배우기",
          "description": "과즙에 효모를 첨가하는 발효체험/내압체트병에 발효 진행/시음 체험/2층 파티룸 운영",
          "price": "미기재"
        }
      ],
      "mainImage": "https://cdn.kihoilbo.co.kr/news/photo/202311/1058962_412778_62.jpg"
    },
    {
      "title": "덕유양조",
      "location": "전라북도 무주군 안성면 장무로 1375-7",
      "phone": "063-323-2355",
      "link": "http://www.meoruwine.co.kr/",
      "alwaysvisit": false,
      "reservation": true,
      "visitcount": 371,
      "number": 55,
      "main": "천마몽 38%",
      "content": "무주 구천동 머루와인및 산머루주는 덕유산이라는 무공해 청정지역을 배경으로 머루의 효능을 와인으로 제조향상에 더욱 노력할 것입니다.",
      "activity": [],
      "mainImage": "https://lh5.googleusercontent.com/proxy/jSLWoc0wvnHkLmR_Wogy5_-Rm2ryVagHayEu8cXr6sWnZnbamw7FJOIIrnX_PMvabp9MXbf9Zm12s2OJbXOZraIhAoPk5S4Vy4PiVSx4h3wwUA"
    }
  ]
}
